<?xml version="1.0" encoding="utf-8"?>
<publishData>
  <publishProfile publishUrl="D:\stagingSites\StingyPrice" deleteExistingFiles="False" ftpAnonymousLogin="False" ftpPassiveMode="True" msdeploySite="" msdeploySiteID="" msdeployRemoteSitePhysicalPath="" msdeployAllowUntrustedCertificate="False" msdeploySkipExtraFilesOnServer="True" msdeployMarkAsApp="False" profileName="Profile1" publishMethod="FileSystem" replaceMatchingFiles="True" userName="" savePWD="False" userPWD="" SelectedForPublish="True">
    <file relUrl="Scripts/2011.2.712/telerik.grid.min.js" publishTime="07/23/2011 23:18:56" />
    <file relUrl="Content/2011.2.712/telerik.office2007.min.css" publishTime="07/23/2011 23:18:56" />
    <file relUrl="Content/2011.2.712/Transparent/hover.png" publishTime="07/23/2011 23:18:56" />
    <file relUrl="Content/2011.2.712/Telerik/treeview-line.png" publishTime="07/23/2011 23:18:56" />
    <file relUrl="App_GlobalResources/GridLocalization.pl-PL.resx" publishTime="07/23/2011 23:18:56" />
    <file relUrl="Content/2011.2.712/Black/slider-h.gif" publishTime="07/23/2011 23:18:56" />
    <file relUrl="Content/2011.2.712/Office2007/sprite-vertical.png" publishTime="07/23/2011 23:18:56" />
    <file relUrl="Content/2011.2.712/Simple/treeview-nodes.png" publishTime="07/23/2011 23:18:56" />
    <file relUrl="App_GlobalResources/UploadLocalization.pl-PL.resx" publishTime="07/23/2011 23:18:56" />
    <file relUrl="Content/2011.2.712/Vista/loading.gif" publishTime="07/23/2011 23:18:56" />
    <file relUrl="bin/System.Web.WebPages.Razor.dll" publishTime="01/05/2011 14:45:38" />
    <file relUrl="Content/2011.2.712/Hay/editor.png" publishTime="07/23/2011 23:18:56" />
    <file relUrl="Content/2011.2.712/Vista/sprite-vertical.png" publishTime="07/23/2011 23:18:56" />
    <file relUrl="Content/2011.2.712/Transparent/slider-h.gif" publishTime="07/23/2011 23:18:56" />
    <file relUrl="Content/2011.2.712/Hay/sprite-vertical.png" publishTime="07/23/2011 23:18:56" />
    <file relUrl="Content/2011.2.712/Office2010Silver/imagebrowser.png" publishTime="07/23/2011 23:18:56" />
    <file relUrl="Content/2011.2.712/Default/slider-h.gif" publishTime="07/23/2011 23:18:56" />
    <file relUrl="bin/Microsoft.Practices.Unity.Configuration.xml" publishTime="04/16/2010 12:17:46" />
    <file relUrl="Views/Web.config" publishTime="07/23/2011 23:18:57" />
    <file relUrl="Content/2011.2.712/Default/loading.gif" publishTime="07/23/2011 23:18:56" />
    <file relUrl="Content/2011.2.712/Telerik/loading.gif" publishTime="07/23/2011 23:18:56" />
    <file relUrl="bin/System.Web.Razor.xml" publishTime="12/20/2010 09:52:36" />
    <file relUrl="bin/Newtonsoft.Json.xml" publishTime="08/08/2011 20:09:53" />
    <file relUrl="Areas/Admin/Views/Home/Index.cshtml" publishTime="08/08/2011 20:09:51" />
    <file relUrl="Scripts/2011.2.712/telerik.grid.editing.min.js" publishTime="07/23/2011 23:18:56" />
    <file relUrl="Content/2011.2.712/Office2010Silver/loading.gif" publishTime="07/23/2011 23:18:56" />
    <file relUrl="Content/2011.2.712/Outlook/slider-h.gif" publishTime="07/23/2011 23:18:56" />
    <file relUrl="bin/StingyPriceDAL.pdb" publishTime="08/08/2011 20:14:46" />
    <file relUrl="Content/2011.2.712/Sitefinity/slider-h.gif" publishTime="07/23/2011 23:18:56" />
    <file relUrl="Content/2011.2.712/Outlook/sprite.png" publishTime="07/23/2011 23:18:56" />
    <file relUrl="Content/2011.2.712/Forest/sprite-vertical.png" publishTime="07/23/2011 23:18:56" />
    <file relUrl="bin/Telerik.Web.Mvc.xml" publishTime="08/03/2011 23:58:06" />
    <file relUrl="App_GlobalResources/EditorLocalization.pl-PL.resx" publishTime="07/23/2011 23:18:56" />
    <file relUrl="Scripts/2011.2.712/telerik.grid.filtering.min.js" publishTime="07/23/2011 23:18:56" />
    <file relUrl="Views/Shared/EditorTemplates/Currency.cshtml" publishTime="07/23/2011 23:18:57" />
    <file relUrl="Content/2011.2.712/Hay/treeview-nodes-rtl.png" publishTime="07/23/2011 23:18:56" />
    <file relUrl="Content/2011.2.712/telerik.webblue.min.css" publishTime="07/23/2011 23:18:56" />
    <file relUrl="Content/2011.2.712/Web20/treeview-line.png" publishTime="07/23/2011 23:18:56" />
    <file relUrl="App_GlobalResources/GridLocalization.en-US.resx" publishTime="07/23/2011 23:18:56" />
    <file relUrl="Content/2011.2.712/telerik.outlook.min.css" publishTime="07/23/2011 23:18:56" />
    <file relUrl="Content/themes/base/jquery.ui.tabs.css" publishTime="07/23/2011 23:18:56" />
    <file relUrl="Content/2011.2.712/Sitefinity/treeview-nodes-rtl.png" publishTime="07/23/2011 23:18:56" />
    <file relUrl="App_GlobalResources/GridLocalization.bg-BG.resx" publishTime="07/23/2011 23:18:56" />
    <file relUrl="Content/2011.2.712/Office2010Blue/editor.png" publishTime="07/23/2011 23:18:56" />
    <file relUrl="Content/2011.2.712/Sitefinity/treeview-line.png" publishTime="07/23/2011 23:18:56" />
    <file relUrl="Content/2011.2.712/Sunset/editor.png" publishTime="07/23/2011 23:18:56" />
    <file relUrl="Content/2011.2.712/Web20/editor.png" publishTime="07/23/2011 23:18:56" />
    <file relUrl="Content/2011.2.712/Office2007/slider-h.gif" publishTime="07/23/2011 23:18:56" />
    <file relUrl="bin/Raven.Http.dll" publishTime="08/08/2011 20:09:54" />
    <file relUrl="Scripts/MicrosoftAjax.debug.js" publishTime="07/23/2011 23:18:56" />
    <file relUrl="Scripts/2011.2.712/telerik.datetimepicker.min.js" publishTime="07/23/2011 23:18:56" />
    <file relUrl="Content/2011.2.712/Office2010Blue/slider-v.gif" publishTime="07/23/2011 23:18:56" />
    <file relUrl="Content/2011.2.712/Office2010Blue/loading.gif" publishTime="07/23/2011 23:18:56" />
    <file relUrl="bin/System.Web.Helpers.dll" publishTime="01/05/2011 14:45:38" />
    <file relUrl="Scripts/2011.2.712/telerik.splitter.min.js" publishTime="07/23/2011 23:18:56" />
    <file relUrl="Content/2011.2.712/Simple/slider-h.gif" publishTime="07/23/2011 23:18:56" />
    <file relUrl="Content/2011.2.712/WebBlue/sprite-vertical.png" publishTime="07/23/2011 23:18:56" />
    <file relUrl="Content/2011.2.712/Default/sprite-vertical.png" publishTime="07/23/2011 23:18:56" />
    <file relUrl="App_GlobalResources/EditorLocalization.de-DE.resx" publishTime="07/23/2011 23:18:56" />
    <file relUrl="Scripts/jquery-1.5.1.min.js" publishTime="07/23/2011 23:18:56" />
    <file relUrl="Content/2011.2.712/telerik.forest.min.css" publishTime="07/23/2011 23:18:56" />
    <file relUrl="bin/Newtonsoft.Json.pdb" publishTime="08/08/2011 20:09:53" />
    <file relUrl="bin/System.Web.Razor.dll" publishTime="01/05/2011 14:45:38" />
    <file relUrl="Content/2011.2.712/Default/treeview-nodes-rtl.png" publishTime="07/23/2011 23:18:56" />
    <file relUrl="bin/Raven.Client.Lightweight.pdb" publishTime="08/08/2011 20:09:54" />
    <file relUrl="Scripts/MicrosoftMvcAjax.js" publishTime="07/23/2011 23:18:56" />
    <file relUrl="Scripts/modernizr-1.7.js" publishTime="07/23/2011 23:18:57" />
    <file relUrl="Content/2011.2.712/Transparent/slider-v.gif" publishTime="07/23/2011 23:18:56" />
    <file relUrl="Content/2011.2.712/Sitefinity/sprite.png" publishTime="07/23/2011 23:18:56" />
    <file relUrl="App_GlobalResources/EditorLocalization.pt-BR.resx" publishTime="07/23/2011 23:18:56" />
    <file relUrl="bin/StingyPrice.dll" publishTime="08/08/2011 21:16:24" />
    <file relUrl="App_GlobalResources/UploadLocalization.bg-BG.resx" publishTime="07/23/2011 23:18:56" />
    <file relUrl="Scripts/2011.2.712/telerik.panelbar.min.js" publishTime="07/23/2011 23:18:56" />
    <file relUrl="Content/2011.2.712/Office2010Black/slider-v.gif" publishTime="07/23/2011 23:18:56" />
    <file relUrl="Scripts/jquery.validate-vsdoc.js" publishTime="07/23/2011 23:18:56" />
    <file relUrl="Scripts/2011.2.712/telerik.common.min.js" publishTime="07/23/2011 23:18:56" />
    <file relUrl="Content/2011.2.712/Office2010Black/imagebrowser.png" publishTime="07/23/2011 23:18:56" />
    <file relUrl="bin/Raven.Client.Lightweight.xml" publishTime="08/08/2011 20:09:54" />
    <file relUrl="Content/2011.2.712/Web20/imagebrowser.png" publishTime="07/23/2011 23:18:56" />
    <file relUrl="App_GlobalResources/GridLocalization.uk-UA.resx" publishTime="07/23/2011 23:18:56" />
    <file relUrl="Content/themes/base/jquery.ui.dialog.css" publishTime="07/23/2011 23:18:56" />
    <file relUrl="bin/Microsoft.Web.Infrastructure.xml" publishTime="12/20/2010 09:52:36" />
    <file relUrl="bin/Lucene.Net.xml" publishTime="08/08/2011 20:09:54" />
    <file relUrl="App_GlobalResources/GridLocalization.pt-BR.resx" publishTime="07/23/2011 23:18:56" />
    <file relUrl="bin/Raven.Munin.pdb" publishTime="08/08/2011 20:09:54" />
    <file relUrl="Content/2011.2.712/telerik.transparent.min.css" publishTime="07/23/2011 23:18:56" />
    <file relUrl="Content/2011.2.712/telerik.simple.min.css" publishTime="07/23/2011 23:18:56" />
    <file relUrl="bin/Raven.Storage.Esent.dll" publishTime="08/08/2011 20:09:54" />
    <file relUrl="Content/2011.2.712/telerik.common.min.css" publishTime="07/23/2011 23:18:56" />
    <file relUrl="Content/2011.2.712/Hay/treeview-line.png" publishTime="07/23/2011 23:18:56" />
    <file relUrl="bin/System.Web.WebPages.xml" publishTime="12/19/2010 22:59:38" />
    <file relUrl="bin/ICSharpCode.NRefactory.dll" publishTime="08/08/2011 20:09:54" />
    <file relUrl="Views/Account/ChangePassword.cshtml" publishTime="07/23/2011 23:18:57" />
    <file relUrl="Content/2011.2.712/Black/sprite-vertical.png" publishTime="07/23/2011 23:18:56" />
    <file relUrl="Content/2011.2.712/Office2010Silver/sprite.png" publishTime="07/23/2011 23:18:56" />
    <file relUrl="Content/2011.2.712/Simple/slider-v.gif" publishTime="07/23/2011 23:18:56" />
    <file relUrl="Content/2011.2.712/Transparent/selected.png" publishTime="07/23/2011 23:18:56" />
    <file relUrl="Content/2011.2.712/Sunset/imagebrowser.png" publishTime="07/23/2011 23:18:56" />
    <file relUrl="Content/2011.2.712/Office2010Silver/sprite-vertical.png" publishTime="07/23/2011 23:18:56" />
    <file relUrl="Views/Shared/EditorTemplates/Integer.cshtml" publishTime="07/23/2011 23:18:57" />
    <file relUrl="Views/Account/Register.cshtml" publishTime="07/23/2011 23:18:57" />
    <file relUrl="Scripts/MicrosoftMvcAjax.debug.js" publishTime="07/23/2011 23:18:56" />
    <file relUrl="Views/Shared/_LogOnPartial.cshtml" publishTime="07/23/2011 23:18:57" />
    <file relUrl="Scripts/jquery.unobtrusive-ajax.js" publishTime="07/23/2011 23:18:56" />
    <file relUrl="Content/2011.2.712/Office2010Silver/slider-v.gif" publishTime="07/23/2011 23:18:56" />
    <file relUrl="Scripts/jquery.validate.unobtrusive.min.js" publishTime="07/23/2011 23:18:57" />
    <file relUrl="Scripts/2011.2.712/telerik.grid.resizing.min.js" publishTime="07/23/2011 23:18:56" />
    <file relUrl="Content/2011.2.712/telerik.black.min.css" publishTime="07/23/2011 23:18:56" />
    <file relUrl="bin/Raven.Http.pdb" publishTime="08/08/2011 20:09:54" />
    <file relUrl="Content/2011.2.712/Windows7/slider-h.gif" publishTime="07/23/2011 23:18:56" />
    <file relUrl="App_GlobalResources/UploadLocalization.en-US.resx" publishTime="07/23/2011 23:18:56" />
    <file relUrl="Scripts/2011.2.712/telerik.draganddrop.min.js" publishTime="07/23/2011 23:18:56" />
    <file relUrl="Content/2011.2.712/Office2010Blue/sprite-vertical.png" publishTime="07/23/2011 23:18:56" />
    <file relUrl="Content/2011.2.712/WebBlue/editor.png" publishTime="07/23/2011 23:18:56" />
    <file relUrl="Scripts/2011.2.712/telerik.autocomplete.min.js" publishTime="07/23/2011 23:18:56" />
    <file relUrl="Content/2011.2.712/Default/treeview-line.png" publishTime="07/23/2011 23:18:56" />
    <file relUrl="bin/System.Web.Mvc.dll" publishTime="01/05/2011 16:42:16" />
    <file relUrl="bin/Raven.Storage.Managed.dll" publishTime="08/08/2011 20:09:54" />
    <file relUrl="Content/2011.2.712/Black/treeview-nodes.png" publishTime="07/23/2011 23:18:56" />
    <file relUrl="Content/2011.2.712/Sunset/treeview-line.png" publishTime="07/23/2011 23:18:56" />
    <file relUrl="bin/System.Web.Mvc.xml" publishTime="02/09/2011 10:26:24" />
    <file relUrl="Content/2011.2.712/WebBlue/treeview-nodes.png" publishTime="07/23/2011 23:18:56" />
    <file relUrl="Content/2011.2.712/Web20/slider-h.gif" publishTime="07/23/2011 23:18:56" />
    <file relUrl="Content/themes/base/images/ui-bg_glass_75_dadada_1x400.png" publishTime="07/23/2011 23:18:56" />
    <file relUrl="Content/2011.2.712/Default/imagebrowser.png" publishTime="07/23/2011 23:18:56" />
    <file relUrl="Content/2011.2.712/Sunset/sprite.png" publishTime="07/23/2011 23:18:56" />
    <file relUrl="Content/2011.2.712/Sunset/sprite-vertical.png" publishTime="07/23/2011 23:18:56" />
    <file relUrl="Scripts/2011.2.712/telerik.calendar.min.js" publishTime="07/23/2011 23:18:56" />
    <file relUrl="Content/2011.2.712/Office2007/treeview-nodes-rtl.png" publishTime="07/23/2011 23:18:56" />
    <file relUrl="Content/2011.2.712/Sitefinity/editor.png" publishTime="07/23/2011 23:18:56" />
    <file relUrl="bin/Lucene.Net.pdb" publishTime="08/08/2011 20:09:54" />
    <file relUrl="Content/2011.2.712/Sitefinity/sprite-vertical.png" publishTime="07/23/2011 23:18:56" />
    <file relUrl="Content/2011.2.712/telerik.vista.min.css" publishTime="07/23/2011 23:18:56" />
    <file relUrl="bin/Esent.Interop.dll" publishTime="08/08/2011 20:09:53" />
    <file relUrl="Content/2011.2.712/Transparent/imagebrowser.png" publishTime="07/23/2011 23:18:56" />
    <file relUrl="Views/Account/ChangePasswordSuccess.cshtml" publishTime="07/23/2011 23:18:57" />
    <file relUrl="Content/2011.2.712/Sunset/treeview-nodes.png" publishTime="07/23/2011 23:18:56" />
    <file relUrl="Content/2011.2.712/Office2010Silver/editor.png" publishTime="07/23/2011 23:18:56" />
    <file relUrl="Content/2011.2.712/Outlook/treeview-nodes-rtl.png" publishTime="07/23/2011 23:18:56" />
    <file relUrl="Views/Shared/EditorTemplates/Date.cshtml" publishTime="07/23/2011 23:18:57" />
    <file relUrl="Views/Shared/Error.cshtml" publishTime="07/23/2011 23:18:57" />
    <file relUrl="Content/2011.2.712/telerik.telerik.min.css" publishTime="07/23/2011 23:18:56" />
    <file relUrl="Scripts/2011.2.712/telerik.list.min.js" publishTime="07/23/2011 23:18:56" />
    <file relUrl="Content/themes/base/images/ui-icons_454545_256x240.png" publishTime="07/23/2011 23:18:56" />
    <file relUrl="App_GlobalResources/EditorLocalization.bg-BG.resx" publishTime="07/23/2011 23:18:56" />
    <file relUrl="Content/2011.2.712/Hay/treeview-nodes.png" publishTime="07/23/2011 23:18:56" />
    <file relUrl="Content/2011.2.712/Black/slider-v.gif" publishTime="07/23/2011 23:18:56" />
    <file relUrl="Content/themes/base/images/ui-bg_flat_0_aaaaaa_40x100.png" publishTime="07/23/2011 23:18:56" />
    <file relUrl="Content/2011.2.712/Sitefinity/slider-v.gif" publishTime="07/23/2011 23:18:56" />
    <file relUrl="Content/2011.2.712/telerik.windows7.min.css" publishTime="07/23/2011 23:18:56" />
    <file relUrl="Content/2011.2.712/Office2010Black/sprite.png" publishTime="07/23/2011 23:18:56" />
    <file relUrl="Views/Shared/_StingyMasterLayout.cshtml" publishTime="08/04/2011 19:40:17" />
    <file relUrl="Content/themes/base/jquery.ui.slider.css" publishTime="07/23/2011 23:18:56" />
    <file relUrl="Global.asax" publishTime="07/23/2011 23:18:56" />
    <file relUrl="Scripts/modernizr-1.7.min.js" publishTime="07/23/2011 23:18:57" />
    <file relUrl="Content/themes/base/jquery.ui.all.css" publishTime="07/23/2011 23:18:56" />
    <file relUrl="Scripts/2011.2.712/telerik.slider.min.js" publishTime="07/23/2011 23:18:56" />
    <file relUrl="Content/2011.2.712/Office2010Black/sprite-vertical.png" publishTime="07/23/2011 23:18:56" />
    <file relUrl="App_GlobalResources/EditorLocalization.ru-RU.resx" publishTime="07/23/2011 23:18:56" />
    <file relUrl="bin/Microsoft.Web.Infrastructure.dll" publishTime="01/05/2011 14:45:38" />
    <file relUrl="Content/2011.2.712/Office2010Silver/slider-h.gif" publishTime="07/23/2011 23:18:56" />
    <file relUrl="Content/2011.2.712/Vista/slider-v.gif" publishTime="07/23/2011 23:18:56" />
    <file relUrl="bin/Microsoft.Practices.Unity.dll" publishTime="04/16/2010 12:20:10" />
    <file relUrl="Content/2011.2.712/Forest/treeview-line.png" publishTime="07/23/2011 23:18:56" />
    <file relUrl="Content/2011.2.712/telerik.office2010blue.min.css" publishTime="07/23/2011 23:18:56" />
    <file relUrl="Content/2011.2.712/Default/editor.png" publishTime="07/23/2011 23:18:56" />
    <file relUrl="Scripts/2011.2.712/telerik.editor.min.js" publishTime="07/23/2011 23:18:56" />
    <file relUrl="bin/System.Web.WebPages.Razor.xml" publishTime="12/20/2010 09:52:36" />
    <file relUrl="Scripts/2011.2.712/jquery-1.5.1.min.js" publishTime="07/23/2011 23:18:56" />
    <file relUrl="bin/AsyncCtpLibrary.dll" publishTime="08/08/2011 20:09:53" />
    <file relUrl="Content/2011.2.712/Black/treeview-nodes-rtl.png" publishTime="07/23/2011 23:18:56" />
    <file relUrl="Views/Home/About.cshtml" publishTime="07/23/2011 23:18:57" />
    <file relUrl="Content/2011.2.712/Transparent/sprite-vertical.png" publishTime="07/23/2011 23:18:56" />
    <file relUrl="Content/2011.2.712/Hay/slider-v.gif" publishTime="07/23/2011 23:18:56" />
    <file relUrl="Content/2011.2.712/Forest/treeview-nodes-rtl.png" publishTime="07/23/2011 23:18:56" />
    <file relUrl="bin/MvcSiteMapProvider.pdb" publishTime="08/03/2011 23:58:06" />
    <file relUrl="Content/2011.2.712/Vista/editor.png" publishTime="07/23/2011 23:18:56" />
    <file relUrl="Content/2011.2.712/Office2010Black/loading.gif" publishTime="07/23/2011 23:18:56" />
    <file relUrl="Content/2011.2.712/Transparent/group.png" publishTime="07/23/2011 23:18:56" />
    <file relUrl="bin/Raven.Storage.Esent.pdb" publishTime="08/08/2011 20:09:54" />
    <file relUrl="Content/2011.2.712/Black/sprite.png" publishTime="07/23/2011 23:18:56" />
    <file relUrl="Content/2011.2.712/Forest/loading.gif" publishTime="07/23/2011 23:18:56" />
    <file relUrl="Content/2011.2.712/Office2010Blue/imagebrowser.png" publishTime="07/23/2011 23:18:56" />
    <file relUrl="Content/2011.2.712/Default/sprite.png" publishTime="07/23/2011 23:18:56" />
    <file relUrl="bin/Newtonsoft.Json.dll" publishTime="08/08/2011 20:09:53" />
    <file relUrl="bin/Spatial.Net.dll" publishTime="08/08/2011 20:09:55" />
    <file relUrl="bin/Telerik.Web.Mvc.dll" publishTime="08/03/2011 23:58:06" />
    <file relUrl="Scripts/jquery-ui-1.8.11.min.js" publishTime="07/23/2011 23:18:56" />
    <file relUrl="bin/SpellChecker.Net.xml" publishTime="08/08/2011 20:09:55" />
    <file relUrl="Content/2011.2.712/Outlook/imagebrowser.png" publishTime="07/23/2011 23:18:56" />
    <file relUrl="Content/2011.2.712/Telerik/slider-h.gif" publishTime="07/23/2011 23:18:56" />
    <file relUrl="Content/2011.2.712/Office2007/treeview-line.png" publishTime="07/23/2011 23:18:56" />
    <file relUrl="Content/2011.2.712/telerik.sitefinity.min.css" publishTime="07/23/2011 23:18:56" />
    <file relUrl="Scripts/2011.2.712/telerik.chart.min.js" publishTime="07/23/2011 23:18:56" />
    <file relUrl="bin/NLog.dll" publishTime="08/08/2011 20:09:52" />
    <file relUrl="Content/2011.2.712/Simple/treeview-nodes-rtl.png" publishTime="07/23/2011 23:18:56" />
    <file relUrl="Content/2011.2.712/Telerik/treeview-nodes.png" publishTime="07/23/2011 23:18:56" />
    <file relUrl="Content/2011.2.712/Windows7/sprite-vertical.png" publishTime="07/23/2011 23:18:56" />
    <file relUrl="Content/2011.2.712/Office2010Black/editor.png" publishTime="07/23/2011 23:18:56" />
    <file relUrl="Scripts/2011.2.712/telerik.combobox.min.js" publishTime="07/23/2011 23:18:56" />
    <file relUrl="Content/2011.2.712/Vista/sprite.png" publishTime="07/23/2011 23:18:56" />
    <file relUrl="Views/Shared/EditorTemplates/Time.cshtml" publishTime="07/23/2011 23:18:57" />
    <file relUrl="Scripts/2011.2.712/telerik.window.min.js" publishTime="07/23/2011 23:18:56" />
    <file relUrl="App_GlobalResources/EditorLocalization.resx" publishTime="07/23/2011 23:18:56" />
    <file relUrl="Scripts/jquery.unobtrusive-ajax.min.js" publishTime="07/23/2011 23:18:56" />
    <file relUrl="Content/2011.2.712/Telerik/sprite.png" publishTime="07/23/2011 23:18:56" />
    <file relUrl="Content/2011.2.712/Telerik/editor.png" publishTime="07/23/2011 23:18:56" />
    <file relUrl="Content/2011.2.712/Telerik/imagebrowser.png" publishTime="07/23/2011 23:18:56" />
    <file relUrl="Content/2011.2.712/Hay/slider-h.gif" publishTime="07/23/2011 23:18:56" />
    <file relUrl="Scripts/2011.2.712/telerik.timepicker.min.js" publishTime="07/23/2011 23:18:56" />
    <file relUrl="bin/Raven.Munin.dll" publishTime="08/08/2011 20:09:54" />
    <file relUrl="Content/2011.2.712/Hay/loading.gif" publishTime="07/23/2011 23:18:56" />
    <file relUrl="Views/Categories/Index.cshtml" publishTime="08/04/2011 19:40:17" />
    <file relUrl="Content/2011.2.712/Office2007/loading.gif" publishTime="07/23/2011 23:18:56" />
    <file relUrl="Scripts/2011.2.712/telerik.grid.reordering.min.js" publishTime="07/23/2011 23:18:56" />
    <file relUrl="Content/2011.2.712/Sunset/loading.gif" publishTime="07/23/2011 23:18:56" />
    <file relUrl="Views/Shared/_StingyPageLayout.cshtml" publishTime="08/08/2011 20:09:52" />
    <file relUrl="bin/Esent.Interop.pdb" publishTime="08/08/2011 20:09:53" />
    <file relUrl="Scripts/jquery-1.5.1.js" publishTime="07/23/2011 23:18:56" />
    <file relUrl="Content/2011.2.712/WebBlue/slider-h.gif" publishTime="07/23/2011 23:18:56" />
    <file relUrl="Content/2011.2.712/Windows7/sprite.png" publishTime="07/23/2011 23:18:56" />
    <file relUrl="Views/Shared/_Layout.cshtml" publishTime="07/23/2011 23:18:57" />
    <file relUrl="Content/2011.2.712/telerik.hay.min.css" publishTime="07/23/2011 23:18:56" />
    <file relUrl="Content/2011.2.712/Office2010Black/treeview-nodes-rtl.png" publishTime="07/23/2011 23:18:56" />
    <file relUrl="Content/2011.2.712/WebBlue/treeview-nodes-rtl.png" publishTime="07/23/2011 23:18:56" />
    <file relUrl="Content/2011.2.712/Hay/imagebrowser.png" publishTime="07/23/2011 23:18:56" />
    <file relUrl="Scripts/2011.2.712/telerik.upload.min.js" publishTime="07/23/2011 23:18:56" />
    <file relUrl="Content/2011.2.712/Sunset/slider-v.gif" publishTime="07/23/2011 23:18:56" />
    <file relUrl="Content/2011.2.712/Office2010Black/treeview-line.png" publishTime="07/23/2011 23:18:56" />
    <file relUrl="Scripts/2011.2.712/jquery.validate.min.js" publishTime="07/23/2011 23:18:56" />
    <file relUrl="Content/2011.2.712/telerik.web20.min.css" publishTime="07/23/2011 23:18:56" />
    <file relUrl="bin/Raven.Database.dll" publishTime="08/08/2011 20:09:54" />
    <file relUrl="App_GlobalResources/EditorLocalization.nl-NL.resx" publishTime="07/23/2011 23:18:56" />
    <file relUrl="Content/2011.2.712/Web20/sprite-vertical.png" publishTime="07/23/2011 23:18:56" />
    <file relUrl="Content/2011.2.712/Forest/slider-v.gif" publishTime="07/23/2011 23:18:56" />
    <file relUrl="Content/2011.2.712/Black/loading.gif" publishTime="07/23/2011 23:18:56" />
    <file relUrl="Content/2011.2.712/Web20/slider-v.gif" publishTime="07/23/2011 23:18:56" />
    <file relUrl="Content/2011.2.712/telerik.office2010black.min.css" publishTime="07/23/2011 23:18:56" />
    <file relUrl="bin/Lucene.Net.dll" publishTime="08/08/2011 20:09:54" />
    <file relUrl="Scripts/2011.2.712/telerik.datepicker.min.js" publishTime="07/23/2011 23:18:56" />
    <file relUrl="bin/Raven.Json.dll" publishTime="08/08/2011 20:09:54" />
    <file relUrl="Content/2011.2.712/Simple/imagebrowser.png" publishTime="07/23/2011 23:18:56" />
    <file relUrl="Content/2011.2.712/Office2007/treeview-nodes.png" publishTime="07/23/2011 23:18:56" />
    <file relUrl="Content/2011.2.712/Office2007/editor.png" publishTime="07/23/2011 23:18:56" />
    <file relUrl="Scripts/jquery.validate.js" publishTime="07/23/2011 23:18:56" />
    <file relUrl="Views/Shared/EditorTemplates/DateTime.cshtml" publishTime="07/23/2011 23:18:57" />
    <file relUrl="Content/2011.2.712/Office2010Silver/gradient.png" publishTime="07/23/2011 23:18:56" />
    <file relUrl="App_GlobalResources/GridLocalization.fr-FR.resx" publishTime="07/23/2011 23:18:56" />
    <file relUrl="Content/2011.2.712/Outlook/sprite-vertical.png" publishTime="07/23/2011 23:18:56" />
    <file relUrl="App_GlobalResources/GridLocalization.resx" publishTime="07/23/2011 23:18:56" />
    <file relUrl="Content/2011.2.712/Office2010Blue/sprite.png" publishTime="07/23/2011 23:18:56" />
    <file relUrl="Content/2011.2.712/Telerik/treeview-nodes-rtl.png" publishTime="07/23/2011 23:18:56" />
    <file relUrl="Content/2011.2.712/Outlook/slider-v.gif" publishTime="07/23/2011 23:18:56" />
    <file relUrl="Content/2011.2.712/Office2010Black/slider-h.gif" publishTime="07/23/2011 23:18:56" />
    <file relUrl="Content/2011.2.712/WebBlue/slider-v.gif" publishTime="07/23/2011 23:18:56" />
    <file relUrl="Content/2011.2.712/Black/imagebrowser.png" publishTime="07/23/2011 23:18:56" />
    <file relUrl="bin/Raven.Client.Embedded.dll" publishTime="08/08/2011 20:09:54" />
    <file relUrl="bin/Microsoft.Practices.Unity.pdb" publishTime="04/16/2010 12:17:46" />
    <file relUrl="Content/2011.2.712/WebBlue/treeview-line.png" publishTime="07/23/2011 23:18:56" />
    <file relUrl="Content/2011.2.712/Outlook/treeview-nodes.png" publishTime="07/23/2011 23:18:56" />
    <file relUrl="Content/2011.2.712/Black/editor.png" publishTime="07/23/2011 23:18:56" />
    <file relUrl="Content/2011.2.712/Windows7/slider-v.gif" publishTime="07/23/2011 23:18:56" />
    <file relUrl="Areas/Admin/Views/Shared/StingyAdminMasterLayout.cshtml" publishTime="08/08/2011 20:09:51" />
    <file relUrl="Views/Products/Search.cshtml" publishTime="08/04/2011 20:20:25" />
    <file relUrl="Content/themes/base/jquery.ui.autocomplete.css" publishTime="07/23/2011 23:18:56" />
    <file relUrl="Views/Home/Index.cshtml" publishTime="07/23/2011 23:18:57" />
    <file relUrl="Content/2011.2.712/Sunset/treeview-nodes-rtl.png" publishTime="07/23/2011 23:18:56" />
    <file relUrl="bin/Microsoft.Practices.Unity.Configuration.dll" publishTime="04/16/2010 12:20:10" />
    <file relUrl="Content/2011.2.712/Office2010Black/treeview-nodes.png" publishTime="07/23/2011 23:18:56" />
    <file relUrl="packages.config" publishTime="08/08/2011 20:09:52" />
    <file relUrl="Content/themes/base/images/ui-bg_glass_95_fef1ec_1x400.png" publishTime="07/23/2011 23:18:56" />
    <file relUrl="Scripts/2011.2.712/telerik.menu.min.js" publishTime="07/23/2011 23:18:56" />
    <file relUrl="App_GlobalResources/GridLocalization.pt-PT.resx" publishTime="07/23/2011 23:18:56" />
    <file relUrl="Scripts/2011.2.712/telerik.treeview.min.js" publishTime="07/23/2011 23:18:56" />
    <file relUrl="bin/Microsoft.Practices.ServiceLocation.dll" publishTime="04/16/2010 12:11:40" />
    <file relUrl="App_GlobalResources/UploadLocalization.ru-RU.resx" publishTime="07/23/2011 23:18:56" />
    <file relUrl="Content/2011.2.712/Office2007/slider-v.gif" publishTime="07/23/2011 23:18:56" />
    <file relUrl="Content/2011.2.712/Windows7/imagebrowser.png" publishTime="07/23/2011 23:18:56" />
    <file relUrl="bin/Raven.Abstractions.dll" publishTime="08/08/2011 20:09:54" />
    <file relUrl="bin/System.Web.Helpers.xml" publishTime="12/19/2010 22:59:38" />
    <file relUrl="Content/Site.css" publishTime="07/23/2011 23:18:56" />
    <file relUrl="Content/themes/base/images/ui-icons_cd0a0a_256x240.png" publishTime="07/23/2011 23:18:56" />
    <file relUrl="Content/themes/base/images/ui-bg_highlight-soft_75_cccccc_1x100.png" publishTime="07/23/2011 23:18:56" />
    <file relUrl="bin/SpellChecker.Net.dll" publishTime="08/08/2011 20:09:55" />
    <file relUrl="Content/themes/base/jquery.ui.selectable.css" publishTime="07/23/2011 23:18:56" />
    <file relUrl="bin/System.Web.WebPages.dll" publishTime="01/05/2011 14:45:38" />
    <file relUrl="Content/2011.2.712/Forest/slider-h.gif" publishTime="07/23/2011 23:18:56" />
    <file relUrl="App_GlobalResources/GridLocalization.es-ES.resx" publishTime="07/23/2011 23:18:56" />
    <file relUrl="Content/2011.2.712/Office2010Blue/slider-h.gif" publishTime="07/23/2011 23:18:56" />
    <file relUrl="Content/2011.2.712/Simple/treeview-line.png" publishTime="07/23/2011 23:18:56" />
    <file relUrl="Content/2011.2.712/telerik.rtl.min.css" publishTime="07/23/2011 23:18:56" />
    <file relUrl="Content/2011.2.712/Vista/slider-h.gif" publishTime="07/23/2011 23:18:56" />
    <file relUrl="Content/themes/base/jquery.ui.progressbar.css" publishTime="07/23/2011 23:18:56" />
    <file relUrl="Content/2011.2.712/Transparent/sprite.png" publishTime="07/23/2011 23:18:56" />
    <file relUrl="Areas/Admin/Views/Shared/StingyAdminPageLayout.cshtml" publishTime="08/08/2011 20:09:51" />
    <file relUrl="Content/2011.2.712/Forest/treeview-nodes.png" publishTime="07/23/2011 23:18:56" />
    <file relUrl="bin/Raven.Json.pdb" publishTime="08/08/2011 20:09:54" />
    <file relUrl="Content/2011.2.712/Vista/imagebrowser.png" publishTime="07/23/2011 23:18:56" />
    <file relUrl="Content/2011.2.712/Web20/loading.gif" publishTime="07/23/2011 23:18:56" />
    <file relUrl="bin/MvcSiteMapProvider.xml" publishTime="08/03/2011 23:58:06" />
    <file relUrl="Scripts/jquery.validate.unobtrusive.js" publishTime="07/23/2011 23:18:57" />
    <file relUrl="Content/2011.2.712/Office2010Blue/gradient.png" publishTime="07/23/2011 23:18:56" />
    <file relUrl="Main.sitemap" publishTime="08/03/2011 23:58:06" />
    <file relUrl="Content/2011.2.712/telerik.sunset.min.css" publishTime="07/23/2011 23:18:56" />
    <file relUrl="App_GlobalResources/EditorLocalization.en-US.resx" publishTime="07/23/2011 23:18:56" />
    <file relUrl="Content/themes/base/images/ui-icons_888888_256x240.png" publishTime="07/23/2011 23:18:56" />
    <file relUrl="Scripts/jquery-ui-1.8.11.js" publishTime="07/23/2011 23:18:56" />
    <file relUrl="Content/2011.2.712/WebBlue/loading.gif" publishTime="07/23/2011 23:18:56" />
    <file relUrl="Areas/Admin/Views/Web.config" publishTime="08/08/2011 20:09:51" />
    <file relUrl="Content/2011.2.712/Default/slider-v.gif" publishTime="07/23/2011 23:18:56" />
    <file relUrl="Content/2011.2.712/WebBlue/imagebrowser.png" publishTime="07/23/2011 23:18:56" />
    <file relUrl="Content/themes/base/jquery.ui.accordion.css" publishTime="07/23/2011 23:18:56" />
    <file relUrl="Content/2011.2.712/Forest/editor.png" publishTime="07/23/2011 23:18:56" />
    <file relUrl="Content/2011.2.712/Transparent/active.png" publishTime="07/23/2011 23:18:56" />
    <file relUrl="bin/Esent.Interop.xml" publishTime="08/08/2011 20:09:54" />
    <file relUrl="bin/Raven.Client.Embedded.pdb" publishTime="08/08/2011 20:09:54" />
    <file relUrl="Content/2011.2.712/Office2007/sprite.png" publishTime="07/23/2011 23:18:56" />
    <file relUrl="Content/2011.2.712/Outlook/treeview-line.png" publishTime="07/23/2011 23:18:56" />
    <file relUrl="Content/2011.2.712/Transparent/widget.png" publishTime="07/23/2011 23:18:56" />
    <file relUrl="Content/2011.2.712/Windows7/loading.gif" publishTime="07/23/2011 23:18:56" />
    <file relUrl="Scripts/MicrosoftAjax.js" publishTime="07/23/2011 23:18:56" />
    <file relUrl="Content/themes/base/jquery.ui.theme.css" publishTime="07/23/2011 23:18:56" />
    <file relUrl="Content/2011.2.712/Sitefinity/imagebrowser.png" publishTime="07/23/2011 23:18:56" />
    <file relUrl="App_GlobalResources/EditorLocalization.fr-FR.resx" publishTime="07/23/2011 23:18:56" />
    <file relUrl="Content/themes/base/jquery.ui.button.css" publishTime="07/23/2011 23:18:56" />
    <file relUrl="Content/themes/base/images/ui-bg_glass_75_e6e6e6_1x400.png" publishTime="07/23/2011 23:18:56" />
    <file relUrl="bin/Raven.Abstractions.pdb" publishTime="08/08/2011 20:09:54" />
    <file relUrl="Content/2011.2.712/Outlook/loading.gif" publishTime="07/23/2011 23:18:56" />
    <file relUrl="Content/2011.2.712/Sitefinity/treeview-nodes.png" publishTime="07/23/2011 23:18:56" />
    <file relUrl="Scripts/MicrosoftMvcValidation.js" publishTime="07/23/2011 23:18:56" />
    <file relUrl="Content/2011.2.712/Telerik/slider-v.gif" publishTime="07/23/2011 23:18:56" />
    <file relUrl="App_GlobalResources/GridLocalization.de-DE.resx" publishTime="07/23/2011 23:18:56" />
    <file relUrl="Content/2011.2.712/Web20/treeview-nodes.png" publishTime="07/23/2011 23:18:56" />
    <file relUrl="Content/themes/base/jquery.ui.base.css" publishTime="07/23/2011 23:18:56" />
    <file relUrl="Content/2011.2.712/Transparent/gradient.png" publishTime="07/23/2011 23:18:56" />
    <file relUrl="Content/2011.2.712/Forest/sprite.png" publishTime="07/23/2011 23:18:56" />
    <file relUrl="Content/themes/base/images/ui-bg_glass_55_fbf9ee_1x400.png" publishTime="07/23/2011 23:18:56" />
    <file relUrl="bin/MvcSiteMapProvider.dll" publishTime="08/03/2011 23:58:06" />
    <file relUrl="Views/Shared/EditorTemplates/Number.cshtml" publishTime="07/23/2011 23:18:57" />
    <file relUrl="Content/2011.2.712/Forest/imagebrowser.png" publishTime="07/23/2011 23:18:56" />
    <file relUrl="Content/2011.2.712/Simple/loading.gif" publishTime="07/23/2011 23:18:56" />
    <file relUrl="bin/StingyPrice.pdb" publishTime="08/08/2011 21:16:23" />
    <file relUrl="Content/2011.2.712/Simple/editor.png" publishTime="07/23/2011 23:18:56" />
    <file relUrl="bin/Microsoft.Practices.Unity.Configuration.pdb" publishTime="04/16/2010 12:17:46" />
    <file relUrl="Content/2011.2.712/telerik.default.min.css" publishTime="07/23/2011 23:18:56" />
    <file relUrl="Scripts/jquery.validate.min.js" publishTime="07/23/2011 23:18:56" />
    <file relUrl="Content/2011.2.712/Default/treeview-nodes.png" publishTime="07/23/2011 23:18:56" />
    <file relUrl="App_GlobalResources/GridLocalization.ru-RU.resx" publishTime="07/23/2011 23:18:56" />
    <file relUrl="Content/2011.2.712/Web20/treeview-nodes-rtl.png" publishTime="07/23/2011 23:18:56" />
    <file relUrl="Content/themes/base/jquery.ui.resizable.css" publishTime="07/23/2011 23:18:56" />
    <file relUrl="Content/2011.2.712/telerik.office2010silver.min.css" publishTime="07/23/2011 23:18:56" />
    <file relUrl="Content/themes/base/images/ui-icons_222222_256x240.png" publishTime="07/23/2011 23:18:56" />
    <file relUrl="Views/Products/Index.cshtml" publishTime="08/04/2011 19:40:17" />
    <file relUrl="Content/2011.2.712/Sunset/slider-h.gif" publishTime="07/23/2011 23:18:56" />
    <file relUrl="Content/2011.2.712/Telerik/sprite-vertical.png" publishTime="07/23/2011 23:18:56" />
    <file relUrl="Content/themes/base/images/ui-bg_flat_75_ffffff_40x100.png" publishTime="07/23/2011 23:18:56" />
    <file relUrl="Content/2011.2.712/Simple/sprite.png" publishTime="07/23/2011 23:18:56" />
    <file relUrl="bin/Raven.Storage.Managed.pdb" publishTime="08/08/2011 20:09:54" />
    <file relUrl="Scripts/2011.2.712/telerik.grid.grouping.min.js" publishTime="07/23/2011 23:18:56" />
    <file relUrl="Scripts/2011.2.712/telerik.imagebrowser.min.js" publishTime="07/23/2011 23:18:56" />
    <file relUrl="Web.config" publishTime="08/08/2011 20:34:54" />
    <file relUrl="Scripts/MicrosoftMvcValidation.debug.js" publishTime="07/23/2011 23:18:56" />
    <file relUrl="bin/Raven.Database.pdb" publishTime="08/08/2011 20:09:54" />
    <file relUrl="bin/StingyPriceDAL.dll" publishTime="08/08/2011 20:14:46" />
    <file relUrl="Content/2011.2.712/Windows7/editor.png" publishTime="07/23/2011 23:18:56" />
    <file relUrl="Scripts/2011.2.712/telerik.tabstrip.min.js" publishTime="07/23/2011 23:18:56" />
    <file relUrl="Content/2011.2.712/Transparent/loading.gif" publishTime="07/23/2011 23:18:56" />
    <file relUrl="Content/themes/base/images/ui-icons_2e83ff_256x240.png" publishTime="07/23/2011 23:18:56" />
    <file relUrl="Views/_ViewStart.cshtml" publishTime="07/23/2011 23:18:57" />
    <file relUrl="bin/NLog.xml" publishTime="08/08/2011 20:09:52" />
    <file relUrl="bin/Microsoft.Practices.Unity.xml" publishTime="04/16/2010 12:17:46" />
    <file relUrl="bin/Raven.Client.Embedded.xml" publishTime="08/08/2011 20:09:54" />
    <file relUrl="bin/Raven.Client.Lightweight.dll" publishTime="08/08/2011 20:09:54" />
    <file relUrl="Content/themes/base/images/ui-bg_glass_65_ffffff_1x400.png" publishTime="07/23/2011 23:18:56" />
    <file relUrl="bin/System.Web.Routing.dll" publishTime="03/18/2010 18:31:26" />
    <file relUrl="Content/2011.2.712/Web20/sprite.png" publishTime="07/23/2011 23:18:56" />
    <file relUrl="Content/2011.2.712/Black/treeview-line.png" publishTime="07/23/2011 23:18:56" />
    <file relUrl="Content/2011.2.712/Simple/sprite-vertical.png" publishTime="07/23/2011 23:18:56" />
    <file relUrl="Content/2011.2.712/Office2007/imagebrowser.png" publishTime="07/23/2011 23:18:56" />
    <file relUrl="Content/2011.2.712/Outlook/editor.png" publishTime="07/23/2011 23:18:56" />
    <file relUrl="Content/2011.2.712/Transparent/toolbar.png" publishTime="07/23/2011 23:18:56" />
    <file relUrl="Scripts/2011.2.712/telerik.textbox.min.js" publishTime="07/23/2011 23:18:56" />
    <file relUrl="Content/2011.2.712/WebBlue/sprite.png" publishTime="07/23/2011 23:18:56" />
    <file relUrl="Views/Account/LogOn.cshtml" publishTime="07/23/2011 23:18:57" />
    <file relUrl="Scripts/jquery-1.5.1-vsdoc.js" publishTime="07/23/2011 23:18:56" />
    <file relUrl="Content/2011.2.712/Sitefinity/loading.gif" publishTime="07/23/2011 23:18:56" />
    <file relUrl="Content/themes/base/jquery.ui.core.css" publishTime="07/23/2011 23:18:56" />
    <file relUrl="Content/2011.2.712/Hay/sprite.png" publishTime="07/23/2011 23:18:56" />
    <file relUrl="App_GlobalResources/EditorLocalization.uk-UA.resx" publishTime="07/23/2011 23:18:56" />
    <file relUrl="Content/2011.2.712/Transparent/editor.png" publishTime="07/23/2011 23:18:56" />
    <file relUrl="Content/themes/base/jquery.ui.datepicker.css" publishTime="07/23/2011 23:18:56" />
  </publishProfile>
</publishData>